atsphinx/stlite/__init__.py
atsphinx/stlite/compat.py
atsphinx/stlite/directives.py
atsphinx/stlite/frame.html.jinja
atsphinx/stlite/nodes.py
atsphinx/stlite/py.typed
atsphinx_stlite-0.2.1.dist-info/METADATA
atsphinx_stlite-0.2.1.dist-info/WHEEL
atsphinx_stlite-0.2.1.dist-info/licenses/LICENSE
atsphinx_stlite-0.2.1.dist-info/RECORD
